trace_dev/__init__.py
trace_dev/cli.py
trace_dev/parser.py
trace_dev/prompt_generator.py
trace_dev/scanner.py
trace_dev-1.0.1.dist-info/licenses/LICENSE
trace_dev-1.0.1.dist-info/METADATA
trace_dev-1.0.1.dist-info/WHEEL
trace_dev-1.0.1.dist-info/entry_points.txt
trace_dev-1.0.1.dist-info/top_level.txt
trace_dev-1.0.1.dist-info/RECORD
