Metadata-Version: 2.4
Name: trace-dev
Version: 1.0.1
Summary: A lightweight Python CLI that generates language-aware, recursive trace prompts for AI-driven development workflows
Home-page: https://github.com/trace-dev/trace-dev
Author: trace-dev
Author-email: dev@trace-dev.com
Classifier: Development Status :: 5 - Production/Stable
Classifier: Intended Audience :: Developers
Classifier: License :: OSI Approved :: MIT License
Classifier: Operating System :: OS Independent
Classifier: Programming Language :: Python :: 3
Classifier: Programming Language :: Python :: 3.11
Classifier: Programming Language :: Python :: 3.12
Requires-Python: >=3.11
License-File: LICENSE
Requires-Dist: click>=8.0.0
Requires-Dist: tree-sitter>=0.20.0
Requires-Dist: tree-sitter-python>=0.20.0
Requires-Dist: tree-sitter-javascript>=0.20.0
Requires-Dist: tree-sitter-typescript>=0.20.0
Requires-Dist: tree-sitter-go>=0.20.0
Requires-Dist: tree-sitter-rust>=0.20.0
Requires-Dist: pyyaml>=6.0
Requires-Dist: pathspec>=0.11.0
Dynamic: author
Dynamic: author-email
Dynamic: classifier
Dynamic: description
Dynamic: description-content-type
Dynamic: home-page
Dynamic: license-file
Dynamic: requires-dist
Dynamic: requires-python
Dynamic: summary
